sshhosts/__init__.py
sshhosts/sshhosts.py
ssh_hosts-0.4.0.dist-info/LICENSE.txt
ssh_hosts-0.4.0.dist-info/METADATA
ssh_hosts-0.4.0.dist-info/WHEEL
ssh_hosts-0.4.0.dist-info/entry_points.txt
ssh_hosts-0.4.0.dist-info/top_level.txt
ssh_hosts-0.4.0.dist-info/RECORD
