Metadata-Version: 2.1
Name: ssh-hosts
Version: 0.4.0
Summary: Quickly connect to host entries from your SSH config file
Author: Christoph Stein
License: MIT
Project-URL: homepage, https://gitlab.com/s7one/ssh-hosts
Project-URL: documentation, https://gitlab.com/s7one/ssh-hosts
Project-URL: repository, https://gitlab.com/s7one/ssh-hosts
Keywords: SSH,Hosts,Network
Classifier: Programming Language :: Python :: 3
Classifier: Development Status :: 4 - Beta
Classifier: Environment :: Console
Requires-Python: >=3.9
License-File: LICENSE.txt
Requires-Dist: Pygments (==2.14.0)
Requires-Dist: wcwidth (==0.2.6)
Requires-Dist: prompt-toolkit (==3.0.38)
